lions/__init__.py
lions/errors.py
lions/lmsg.py
lions/main.py
lions/yaml_parser.py
lions/cpp_gen/__init__.py
lions/cpp_gen/cpp_generator.py
lions/cpp_gen/templates/lions.cpp.jinja
lions/cpp_gen/templates/lions.hpp.jinja
lions/cpp_gen/templates/msg.cpp.jinja
lions/cpp_gen/templates/msg.hpp.jinja
lions/js_gen/__init__.py
lions/js_gen/js_generator.py
lions/ts_gen/__init__.py
lions/ts_gen/ts_generator.py
tests/__init__.py
tests/test_cpp_gen.py
tests/test_js_gen copy.py
tests/test_js_gen.py
tests/test_lmsg.py
tests/test_python_gen.py
tests/test_ts_gen.py
tests/test_yaml_parser.py
lions-1.4.5.dist-info/LICENSE
lions-1.4.5.dist-info/METADATA
lions-1.4.5.dist-info/WHEEL
lions-1.4.5.dist-info/entry_points.txt
lions-1.4.5.dist-info/top_level.txt
lions-1.4.5.dist-info/RECORD
