Metadata-Version: 2.1
Name: lions
Version: 1.4.5
Summary: LIONS (Lightweight IoT Network Specification) is a communication protocol designed for IoT mesh/ad hoc networks. It facilitates seamless communication between devices and includes code generation based on message files (yaml), streamlining development and implementation processes.
Home-page: https://github.com/ItsNotSoftware/lions
Author: Diogo Ferreira
Author-email: itsnotsoftware@gmail.com
License: MIT
Classifier: Programming Language :: Python :: 3
Classifier: License :: OSI Approved :: MIT License
Classifier: Operating System :: OS Independent
License-File: LICENSE
Requires-Dist: pydantic
Requires-Dist: pyyaml
Requires-Dist: jinja2
Requires-Dist: pytest
Requires-Dist: colorama
Provides-Extra: dev
Requires-Dist: twine >=4.0.2 ; extra == 'dev'
